[{"label":"那大镇","value":"460401"},{"label":"和庆镇","value":"460402"},{"label":"南丰镇","value":"460403"},{"label":"大成镇","value":"460404"},{"label":"雅星镇","value":"460405"},{"label":"兰洋镇","value":"460406"},{"label":"光村镇","value":"460407"},{"label":"木棠镇","value":"460408"},{"label":"海头镇","value":"460409"},{"label":"峨蔓镇","value":"460410"},{"label":"王五镇","value":"460411"},{"label":"白马井镇","value":"460412"},{"label":"中和镇","value":"460413"},{"label":"排浦镇","value":"460414"},{"label":"东成镇","value":"460415"},{"label":"新州镇","value":"460416"},{"label":"洋浦经济开发区","value":"460417"},{"label":"华南热作学院","value":"460418"}]