[{"label":"五指山市","value":"469001"},{"label":"琼海市","value":"469002"},{"label":"文昌市","value":"469005"},{"label":"万宁市","value":"469006"},{"label":"东方市","value":"469007"},{"label":"定安县","value":"469021"},{"label":"屯昌县","value":"469022"},{"label":"澄迈县","value":"469023"},{"label":"临高县","value":"469024"},{"label":"白沙黎族自治县","value":"469025"},{"label":"昌江黎族自治县","value":"469026"},{"label":"乐东黎族自治县","value":"469027"},{"label":"陵水黎族自治县","value":"469028"},{"label":"保亭黎族苗族自治县","value":"469029"},{"label":"琼中黎族苗族自治县","value":"469030"}]